spectacle/__init__.py
spectacle/_spectral_convolution.py
spectacle/_xyz.py
spectacle/analyse.py
spectacle/bias_readnoise.py
spectacle/calibrate.py
spectacle/camera.py
spectacle/config.py
spectacle/dark.py
spectacle/flat.py
spectacle/gain.py
spectacle/general.py
spectacle/io.py
spectacle/iso.py
spectacle/linearity.py
spectacle/metadata.py
spectacle/plot.py
spectacle/raw.py
spectacle/raw2.py
spectacle/spectral.py
spectacle/wavelength.py
pyspectacle-3.1.2.dist-info/LICENSE
pyspectacle-3.1.2.dist-info/METADATA
pyspectacle-3.1.2.dist-info/WHEEL
pyspectacle-3.1.2.dist-info/top_level.txt
pyspectacle-3.1.2.dist-info/RECORD
