Metadata-Version: 2.1
Name: pyspectacle
Version: 3.1.2
Summary: SPECTACLE camera calibration module
Home-page: https://github.com/monocle-h2020/camera_calibration
Author: Olivier Burggraaff
Author-email: burggraaff@strw.leidenuniv.nl
License: UNKNOWN
Platform: UNKNOWN
Classifier: Programming Language :: Python :: 3
Classifier: Operating System :: OS Independent
Classifier: Development Status :: 5 - Production/Stable
Classifier: License :: OSI Approved :: GNU General Public License v3 (GPLv3)
Requires-Python: >=3.6
License-File: LICENSE
Requires-Dist: numpy
Requires-Dist: scipy
Requires-Dist: matplotlib
Requires-Dist: rawpy
Requires-Dist: exifread
Requires-Dist: astropy
